aind_behavior_experiment_launcher/__init__.py
aind_behavior_experiment_launcher/logging_helper.py
aind_behavior_experiment_launcher/py.typed
aind_behavior_experiment_launcher/services.py
aind_behavior_experiment_launcher/apps/__init__.py
aind_behavior_experiment_launcher/apps/_base.py
aind_behavior_experiment_launcher/apps/bonsai.py
aind_behavior_experiment_launcher/apps/python_script.py
aind_behavior_experiment_launcher/data_mapper/__init__.py
aind_behavior_experiment_launcher/data_mapper/_base.py
aind_behavior_experiment_launcher/data_mapper/aind_data_schema.py
aind_behavior_experiment_launcher/data_mapper/helpers.py
aind_behavior_experiment_launcher/data_transfer/__init__.py
aind_behavior_experiment_launcher/data_transfer/_base.py
aind_behavior_experiment_launcher/data_transfer/aind_watchdog.py
aind_behavior_experiment_launcher/data_transfer/robocopy.py
aind_behavior_experiment_launcher/launcher/__init__.py
aind_behavior_experiment_launcher/launcher/_base.py
aind_behavior_experiment_launcher/launcher/behavior_launcher.py
aind_behavior_experiment_launcher/launcher/cli.py
aind_behavior_experiment_launcher/launcher/git_manager.py
aind_behavior_experiment_launcher/records/__init__.py
aind_behavior_experiment_launcher/records/subject.py
aind_behavior_experiment_launcher/resource_monitor/__init__.py
aind_behavior_experiment_launcher/resource_monitor/_base.py
aind_behavior_experiment_launcher/resource_monitor/_constraints.py
aind_behavior_experiment_launcher/ui/__init__.py
aind_behavior_experiment_launcher/ui/picker.py
aind_behavior_experiment_launcher/ui/ui_helper.py
aind_behavior_experiment_launcher-0.4.2.dist-info/METADATA
aind_behavior_experiment_launcher-0.4.2.dist-info/WHEEL
aind_behavior_experiment_launcher-0.4.2.dist-info/top_level.txt
aind_behavior_experiment_launcher-0.4.2.dist-info/RECORD
