Metadata-Version: 2.4
Name: aind-behavior-experiment-launcher
Version: 0.4.2
Summary: A library for a minimal framework that can be used to build experimental interfaces.
Author-email: Bruno Cruz <bruno.cruz@alleninstitute.org>
License: MIT
Project-URL: Documentation, https://allenneuraldynamics.github.io/Aind.Behavior.ExperimentLauncher/
Project-URL: Repository, https://github.com/AllenNeuralDynamics/Aind.Behavior.ExperimentLauncher/
Project-URL: Issues, https://github.com/AllenNeuralDynamics/Aind.Behavior.ExperimentLauncher/issues
Project-URL: Changelog, https://github.com/AllenNeuralDynamics/Aind.Behavior.ExperimentLauncher/releases
Classifier: Programming Language :: Python :: 3.11
Classifier: License :: OSI Approved :: MIT License
Classifier: Operating System :: Microsoft :: Windows
Requires-Python: >=3.11
Requires-Dist: pydantic<3.0,>=2.7
Requires-Dist: pydantic-settings
Requires-Dist: gitpython
Requires-Dist: semver
Requires-Dist: rich
Requires-Dist: aind_behavior_services<1
Requires-Dist: aind-slims-api
Provides-Extra: aind-services
Requires-Dist: aind-watchdog-service; extra == "aind-services"
Requires-Dist: aind-data-schema<2; extra == "aind-services"
Provides-Extra: dev
Requires-Dist: ruff; extra == "dev"
Requires-Dist: codespell; extra == "dev"
Requires-Dist: coverage; extra == "dev"
Requires-Dist: aind-behavior-experiment-launcher[aind-services]; extra == "dev"
Provides-Extra: docs
Requires-Dist: aind-behavior-experiment-launcher[aind-services]; extra == "docs"
Requires-Dist: Sphinx<7.3; extra == "docs"
Requires-Dist: furo; extra == "docs"
Requires-Dist: sphinx-jinja; extra == "docs"
Requires-Dist: sphinx-jsonschema; extra == "docs"
Requires-Dist: sphinx-copybutton; extra == "docs"
Requires-Dist: sphinx_mdinclude; extra == "docs"
Requires-Dist: autodoc_pydantic; extra == "docs"
